{
  "userType": "Supervisor",
  "MenuItems": [
    {
      "label": "Home",
      "key": "profileHome",
      "isDefault": false,
      "submenu": [
        {
          "label": "",
          "key": "Home-Master",
          "isDefault": true,
          "submenu": []
        }
      ]
    },
       {
      "label": "Instructions",
      "key": "instructions",
      "isDefault": false,
      "submenu": [
        {
          "label": "",
          "key": "Instructions-Instructions",
          "isDefault": true,
          "submenu": []
        }
      ]
    },
    {
      "label": "My Surveys",
      "key": "mysurvey",
      "isDefault": false,
      "submenu": [
        {
          "label": "Overview",
          "key": "mysurvey-SurveyOverview",
          "isDefault": true,
          "submenu": []
        },
        {
          "label": "Mandatory",
          "key": "mysurvey-Mandatory",
          "isDefault": false,
          "submenu": []
        },
	{
          "label": "Supervisor",
          "key": "mysurvey-Supervisor",
          "isDefault": false,
          "submenu": []
        },
	{
          "label": "Highly Desirable",
          "key": "mysurvey-HighlyDesirable",
          "isDefault": false,
          "submenu": []
        },
        {
          "label": "Desirable",
          "key": "mysurvey-Desirable",
          "isDefault": false,
          "submenu": []
        }
      ]
    },
  
    {
      "label": "My Reports",
      "key": "myreport",
      "isDefault": false,
      "submenu": [
        {
          "label": "Skills Gap Analysis Report",
          "key": "myreport-Report",
          "isDefault": false,
          "submenu": []
        }
      ]
    }
  ]
}